limestone_finance/__init__.py
limestone_finance-0.0.2.dist-info/METADATA
limestone_finance-0.0.2.dist-info/WHEEL
limestone_finance-0.0.2.dist-info/top_level.txt
limestone_finance-0.0.2.dist-info/RECORD
